avio/__init__.py
avio/avio.cpython-313-aarch64-linux-gnu.so
avio/libSDL2-2.0.so.0
avio/libavcodec.so.62
avio/libavfilter.so.11
avio/libavformat.so.62
avio/libavutil.so.60
avio/libfdk-aac.so.2
avio/libswresample.so.6
avio/libswscale.so.9
avio/libx264.so.165
avio.libs/libdrm-7ea97f77.so.2.4.0
avio-3.2.7.dist-info/METADATA
avio-3.2.7.dist-info/WHEEL
avio-3.2.7.dist-info/top_level.txt
avio-3.2.7.dist-info/RECORD
avio-3.2.7.dist-info/licenses/LICENSE
avio-3.2.7.dist-info/sboms/auditwheel.cdx.json
