Metadata-Version: 2.4
Name: avio
Version: 3.2.7
Summary: A python module for processing media streams
Author: Stephen Rhodes
Author-email: Stephen Rhodes <sr99622@gmail.com>
License-Expression: Apache-2.0
Project-URL: Homepage, https://github.com/sr99622/libavio
Project-URL: Bug Tracker, https://github.com/sr99622/libavio/issues
Classifier: Programming Language :: Python :: 3
Classifier: Operating System :: OS Independent
Requires-Python: >=3.10
License-File: LICENSE
Dynamic: author
Dynamic: license-file
Dynamic: requires-python
